shanaproject/__init__.py
shanaproject/__main__.py
shanaproject/model.py
shanaproject/parser.py
shanaproject_api-0.2.0.dist-info/METADATA
shanaproject_api-0.2.0.dist-info/WHEEL
shanaproject_api-0.2.0.dist-info/entry_points.txt
shanaproject_api-0.2.0.dist-info/top_level.txt
shanaproject_api-0.2.0.dist-info/zip-safe
shanaproject_api-0.2.0.dist-info/RECORD
