Metadata-Version: 2.1
Name: shanaproject-api
Version: 0.2.0
Summary: Python API for https://www.shanaproject.com/.
Home-page: https://gitlab.com/Fading_/shanaproject-api
Author: Fading
Author-email: fading@miracle.org
License: MIT
Platform: UNKNOWN
Requires-Python: >=3.5.0,<4.0.0
Requires-Dist: beautifulsoup4 (<5.0.0,>=4.9.3)
Requires-Dist: requests (<3.0.0,>=2.24.0)
Requires-Dist: databind.json (<1.0.0,>=0.6.1)
